{
    "Ar36": {
        "error": 0.00045491133794883505, 
        "filter_outliers_dict": {
            "filter_outliers": true, 
            "iterations": 1, 
            "std_devs": 2
        }, 
        "fit": "Linear", 
        "value": 0.01973577674316205
    }, 
    "Ar37": {
        "error": 0.011588233369844466, 
        "filter_outliers_dict": {
            "filter_outliers": true, 
            "iterations": 1, 
            "std_devs": 2
        }, 
        "fit": "linear", 
        "value": 0.37702408777390783
    }, 
    "Ar38": {
        "error": 0.006234851814973649, 
        "filter_outliers_dict": {
            "filter_outliers": true, 
            "iterations": 1, 
            "std_devs": 2
        }, 
        "fit": "linear", 
        "value": 1.3623562508212763
    }, 
    "Ar39": {
        "error": 0.02418573950118509, 
        "filter_outliers_dict": {
            "filter_outliers": true, 
            "iterations": 1, 
            "std_devs": 2
        }, 
        "fit": "Linear", 
        "value": 108.35944535476207
    }, 
    "Ar40": {
        "error": 0.04067179348453015, 
        "filter_outliers_dict": {
            "filter_outliers": true, 
            "iterations": 1, 
            "std_devs": 2
        }, 
        "fit": "Linear", 
        "value": 376.12804577385543
    }, 
    "PM41": {
        "error": 0.07398030702991089, 
        "filter_outliers_dict": {
            "filter_outliers": false, 
            "iterations": 1, 
            "std_devs": 2
        }, 
        "fit": "linear", 
        "value": -0.10282043389292406
    }
}