{
    "Ar36": {
        "error": 0.000332372194613401, 
        "filter_outliers_dict": {
            "filter_outliers": true, 
            "iterations": 1, 
            "std_devs": 2
        }, 
        "fit": "Linear", 
        "value": 0.013376445678194586
    }, 
    "Ar37": {
        "error": 0.012401778335790432, 
        "filter_outliers_dict": {
            "filter_outliers": true, 
            "iterations": 1, 
            "std_devs": 2
        }, 
        "fit": "linear", 
        "value": 0.16953526663653906
    }, 
    "Ar38": {
        "error": 0.005762311618092016, 
        "filter_outliers_dict": {
            "filter_outliers": true, 
            "iterations": 1, 
            "std_devs": 2
        }, 
        "fit": "linear", 
        "value": 0.6271665279125912
    }, 
    "Ar39": {
        "error": 0.018533424133944678, 
        "filter_outliers_dict": {
            "filter_outliers": true, 
            "iterations": 1, 
            "std_devs": 2
        }, 
        "fit": "Linear", 
        "value": 49.82302789800726
    }, 
    "Ar40": {
        "error": 0.026500849620633198, 
        "filter_outliers_dict": {
            "filter_outliers": true, 
            "iterations": 1, 
            "std_devs": 2
        }, 
        "fit": "Linear", 
        "value": 208.4345733101075
    }, 
    "PM41": {
        "error": 0.06520915600079898, 
        "filter_outliers_dict": {
            "filter_outliers": false, 
            "iterations": 1, 
            "std_devs": 2
        }, 
        "fit": "linear", 
        "value": -0.054732203431468604
    }
}