{
    "Ar36": {
        "error": 0.00029116953980893304, 
        "filter_outliers_dict": {
            "filter_outliers": true, 
            "iterations": 1, 
            "std_devs": 2
        }, 
        "fit": "Linear", 
        "value": 0.009673961503013874
    }, 
    "Ar37": {
        "error": 0.010094278244473417, 
        "filter_outliers_dict": {
            "filter_outliers": true, 
            "iterations": 1, 
            "std_devs": 2
        }, 
        "fit": "linear", 
        "value": 0.197056745173824
    }, 
    "Ar38": {
        "error": 0.005059697805960725, 
        "filter_outliers_dict": {
            "filter_outliers": true, 
            "iterations": 1, 
            "std_devs": 2
        }, 
        "fit": "linear", 
        "value": 0.18784215447358427
    }, 
    "Ar39": {
        "error": 0.014201692989908575, 
        "filter_outliers_dict": {
            "filter_outliers": true, 
            "iterations": 1, 
            "std_devs": 2
        }, 
        "fit": "Linear", 
        "value": 14.7218114486591
    }, 
    "Ar40": {
        "error": 0.018136138031033346, 
        "filter_outliers_dict": {
            "filter_outliers": true, 
            "iterations": 1, 
            "std_devs": 2
        }, 
        "fit": "Linear", 
        "value": 61.35940348772134
    }, 
    "PM41": {
        "error": 0.08481934158467767, 
        "filter_outliers_dict": {
            "filter_outliers": false, 
            "iterations": 1, 
            "std_devs": 2
        }, 
        "fit": "linear", 
        "value": -0.06758331865493516
    }
}