{
    "AX": {
        "error": 0.005801744975935135, 
        "filter_outliers_dict": {
            "filter_outliers": true, 
            "iterations": 1, 
            "std_devs": 2
        }, 
        "fit": "average", 
        "value": -0.07048136434911333
    }, 
    "CDD": {
        "error": 1.9150460293477776e-05, 
        "filter_outliers_dict": {
            "filter_outliers": true, 
            "iterations": 1, 
            "std_devs": 10
        }, 
        "fit": "average", 
        "value": 0.0001612708636494439
    }, 
    "H1": {
        "error": 0.005860699657829014, 
        "filter_outliers_dict": {
            "filter_outliers": true, 
            "iterations": 1, 
            "std_devs": 2
        }, 
        "fit": "average", 
        "value": -0.0060620178981303586
    }, 
    "H2": {
        "error": 0.007250464193591694, 
        "filter_outliers_dict": {
            "filter_outliers": true, 
            "iterations": 1, 
            "std_devs": 2
        }, 
        "fit": "average", 
        "value": -0.21195905697111067
    }, 
    "L1": {
        "error": 0.0024663183190299087, 
        "filter_outliers_dict": {
            "filter_outliers": true, 
            "iterations": 1, 
            "std_devs": 2
        }, 
        "fit": "average", 
        "value": -0.02603696923682041
    }, 
    "L2": {
        "error": 0.005482077073230817, 
        "filter_outliers_dict": {
            "filter_outliers": true, 
            "iterations": 1, 
            "std_devs": 2
        }, 
        "fit": "average", 
        "value": -0.023603349866582662
    }
}