{
    "Ar36": {
        "error": 0.00041225116722771804, 
        "filter_outliers_dict": {
            "filter_outliers": true, 
            "iterations": 1, 
            "std_devs": 2
        }, 
        "fit": "Linear", 
        "value": 0.029329330320086368
    }, 
    "Ar37": {
        "error": 0.011896170788584385, 
        "filter_outliers_dict": {
            "filter_outliers": true, 
            "iterations": 1, 
            "std_devs": 2
        }, 
        "fit": "linear", 
        "value": 0.027012982580682812
    }, 
    "Ar38": {
        "error": 0.005079987621081315, 
        "filter_outliers_dict": {
            "filter_outliers": true, 
            "iterations": 1, 
            "std_devs": 2
        }, 
        "fit": "linear", 
        "value": 0.8529769961367133
    }, 
    "Ar39": {
        "error": 0.01930575755290276, 
        "filter_outliers_dict": {
            "filter_outliers": true, 
            "iterations": 1, 
            "std_devs": 2
        }, 
        "fit": "Linear", 
        "value": 66.29521325118878
    }, 
    "Ar40": {
        "error": 0.046839453487084806, 
        "filter_outliers_dict": {
            "filter_outliers": true, 
            "iterations": 1, 
            "std_devs": 2
        }, 
        "fit": "Linear", 
        "value": 826.03244025272
    }, 
    "PM41": {
        "error": 0.071430666836247, 
        "filter_outliers_dict": {
            "filter_outliers": false, 
            "iterations": 1, 
            "std_devs": 2
        }, 
        "fit": "linear", 
        "value": -0.09295988433511701
    }
}